{
  "schemaVersion": "1.0",
  "id": "serum-lesson-000-stub",
  "presetName": "ExampleInitPluck",
  "style": "tutorial-stub",
  "mappings": {
    "oscillatorA.waveform": "saw",
    "filter.cutoffHz": 3200,
    "ampEnv.decayMs": 180,
    "unison.voices": 3,
    "unison.detuneCents": 12
  },
  "character": "Short bright pluck with width from light unison.",
  "causalReasoning": "Fast amp decay keeps it percussive; medium-high cutoff lets harmonics through so the saw reads as plucky, not boomy; a few detuned voices add shimmer without turning into a supersaw pad.",
  "tags": ["pluck", "bright", "init-style"]
}
